linkedin_ai/__init__.py
linkedin_ai/_version.py
linkedin_ai/app.py
linkedin_ai/jobai.py
linkedin_ai/jobdb.py
linkedin_ai/liautomator.py
linkedin_ai/models.py
linkedin_ai/core/__init__.py
linkedin_ai/core/aimanager.py
linkedin_ai/core/sqldantic.py
linkedin_ai/widgets/__init__.py
linkedin_ai/widgets/checkablecombobox.py
linkedin_ai/widgets/comboboxwithupdatebuttons.py
linkedin_ai/widgets/dynamicsignalqobject.py
linkedin_ai/widgets/fileselectwidget.py
linkedin_ai/widgets/jobappdbwidgets.py
linkedin_ai/widgets/logindialog.py
linkedin_ai/widgets/modeltablewidget.py
linkedin_ai/widgets/questiondialog.py
linkedin_ai/widgets/searchapplywidget.py
linkedin_ai/widgets/settingswidget.py
linkedin_ai-0.6.6.dist-info/LICENSE
linkedin_ai-0.6.6.dist-info/METADATA
linkedin_ai-0.6.6.dist-info/WHEEL
linkedin_ai-0.6.6.dist-info/entry_points.txt
linkedin_ai-0.6.6.dist-info/top_level.txt
linkedin_ai-0.6.6.dist-info/RECORD
