Metadata-Version: 2.1
Name: linkedin-ai
Version: 0.6.6
Summary: Automate searching for jobs and submitting applications on LinkedIn using OpenAI
Home-page: https://github.com/LucasFaudman/linkedin-ai.git
Author: Lucas Faudman
Author-email: Lucas Faudman <lucasfaudman@gmail.com>
License: GNU GENERAL PUBLIC LICENSE
Project-URL: Homepage, https://github.com/LucasFaudman/linkedin-ai.git
Project-URL: Repository, https://github.com/LucasFaudman/linkedin-ai.git
Keywords: linkedin,openai,automation,job,applications,ai,linkedin-ai,linkedin scraper,linkedin job applications,linkedin automation,selenium,bs4,PyQt5,gui
Classifier: Development Status :: 4 - Beta
Classifier: License :: OSI Approved :: MIT License
Classifier: Programming Language :: Python :: 3
Classifier: Programming Language :: Python :: 3.7
Classifier: Programming Language :: Python :: 3.8
Classifier: Programming Language :: Python :: 3.9
Classifier: Programming Language :: Python :: 3.10
Classifier: Programming Language :: Python :: 3.11
Classifier: Operating System :: OS Independent
Requires-Python: >=3.7
License-File: LICENSE
Requires-Dist: souperscraper
Requires-Dist: openai
Requires-Dist: tiktoken
Requires-Dist: pydantic
Requires-Dist: python-docx
Requires-Dist: pyqt5
